setup.cfg
setup.py
external_algn_tools/__init__.py
external_algn_tools/bowtie_tools.py
external_algn_tools/config.py
external_algn_tools/custom_sam_utils.py
seqtables/__init__.py
seqtables.egg-info/PKG-INFO
seqtables.egg-info/SOURCES.txt
seqtables.egg-info/dependency_links.txt
seqtables.egg-info/requires.txt
seqtables.egg-info/top_level.txt
seqtables/core/__init__.py
seqtables/core/library_utils.py
seqtables/core/numpy_ops.py
seqtables/core/seq_logo.py
seqtables/core/seq_tables_depr.py
seqtables/core/seqtables.py
seqtables/core/internals/__init__.py
seqtables/core/internals/constructor_ops.py
seqtables/core/internals/sam_cython_setup.py
seqtables/core/internals/cython/sam_to_arr.pyx
seqtables/core/utils/__init__.py
seqtables/core/utils/alphabets.py
seqtables/core/utils/custom_sam_utils.py
seqtables/core/utils/insilica_sequences.py
seqtables/core/utils/seq_table_util.py
seqtables/core/utils/unique_ops.py
seqtables/io/__init__.py
seqtables/io/read_sequences.py
seqtables/io/scratch_data.py
seqtables/io/write_sequences.py
seqtables/xarray_mods/__init__.py
seqtables/xarray_mods/duck_array_ops.py
seqtables/xarray_mods/st_commons.py
seqtables/xarray_mods/st_merge.py